mcp_eval/__init__.py
mcp_eval/catalog.py
mcp_eval/config.py
mcp_eval/core.py
mcp_eval/datasets.py
mcp_eval/gen_tests.py
mcp_eval/generation.py
mcp_eval/llm_client.py
mcp_eval/metrics.py
mcp_eval/pytest_plugin.py
mcp_eval/runner.py
mcp_eval/session.py
mcp_eval/state_isolation.py
mcp_eval/utils.py
mcp_eval/cli/__init__.py
mcp_eval/cli/doctor.py
mcp_eval/cli/generator.py
mcp_eval/cli/issue.py
mcp_eval/cli/list_command.py
mcp_eval/cli/models.py
mcp_eval/cli/utils.py
mcp_eval/cli/validate.py
mcp_eval/data/utils.py
mcp_eval/data/sample/README.md
mcp_eval/data/sample/__init__.py
mcp_eval/data/sample/mcpeval.secrets.yaml.example
mcp_eval/data/sample/mcpeval.yaml
mcp_eval/data/sample/sample_server.eval.py
mcp_eval/data/sample/sample_server.py
mcp_eval/data/sample/usage_example.py
mcp_eval/data/subagents/README.md
mcp_eval/data/subagents/example-config.yaml
mcp_eval/data/subagents/mcp-eval-config-expert.md
mcp_eval/data/subagents/mcp-eval-debugger.md
mcp_eval/data/subagents/mcp-eval-test-generator.md
mcp_eval/data/subagents/mcp-eval-test-writer.md
mcp_eval/data/subagents/test-assertion-refiner.md
mcp_eval/data/subagents/test-code-emitter.md
mcp_eval/data/subagents/test-scenario-designer.md
mcp_eval/evaluators/__init__.py
mcp_eval/evaluators/base.py
mcp_eval/evaluators/equals_expected.py
mcp_eval/evaluators/exact_tool_count.py
mcp_eval/evaluators/is_instance.py
mcp_eval/evaluators/llm_judge.py
mcp_eval/evaluators/max_iterations.py
mcp_eval/evaluators/multi_criteria_judge.py
mcp_eval/evaluators/not_contains.py
mcp_eval/evaluators/path_efficiency.py
mcp_eval/evaluators/response_contains.py
mcp_eval/evaluators/response_time_check.py
mcp_eval/evaluators/shared.py
mcp_eval/evaluators/tool_called_with.py
mcp_eval/evaluators/tool_failed.py
mcp_eval/evaluators/tool_output_matches.py
mcp_eval/evaluators/tool_sequence.py
mcp_eval/evaluators/tool_success_rate.py
mcp_eval/evaluators/tool_was_called.py
mcp_eval/optimizer/README.md
mcp_eval/optimizer/__init__.py
mcpevals-0.1.10.dist-info/METADATA
mcpevals-0.1.10.dist-info/WHEEL
mcpevals-0.1.10.dist-info/entry_points.txt
mcpevals-0.1.10.dist-info/licenses/LICENSE
mcpevals-0.1.10.dist-info/RECORD
