Metadata-Version: 2.4
Name: mcpevals
Version: 0.1.10
Summary: Pytest-style framework for evaluating Model Context Protocol (MCP) servers.
Author-email: Sarmad Qadri <sarmad@lastmileai.dev>, Jerron Lim <jerron@lastmileai.dev>
License:                                  Apache License
License-File: LICENSE
Requires-Python: >=3.10
Requires-Dist: anthropic>=0.34.0
Requires-Dist: dspy>=2.6.27
Requires-Dist: jinja2>=3.1.6
Requires-Dist: mcp-agent>=0.1.15
Requires-Dist: opentelemetry-api>=1.34.1
Requires-Dist: opentelemetry-exporter-otlp>=1.34.1
Requires-Dist: opentelemetry-sdk>=1.34.1
Requires-Dist: pydantic>=2.11.5
Requires-Dist: pytest>=8.4.0
Requires-Dist: pyyaml>=6.0.2
Requires-Dist: rich>=13.9.4
Requires-Dist: typer>=0.16.0
Provides-Extra: dev
Requires-Dist: httpx>=0.28.1; extra == 'dev'
Requires-Dist: pre-commit>=4.0.1; extra == 'dev'
Requires-Dist: pydantic>=2.10.4; extra == 'dev'
Requires-Dist: pytest-asyncio>=0.21.1; extra == 'dev'
Requires-Dist: pytest-cov>=6.1.1; extra == 'dev'
Requires-Dist: pytest>=7.4.0; extra == 'dev'
Requires-Dist: pyyaml>=6.0.2; extra == 'dev'
Requires-Dist: ruff>=0.8.4; extra == 'dev'
Requires-Dist: tomli>=2.2.1; extra == 'dev'
Requires-Dist: trio>=0.30.0; extra == 'dev'
Provides-Extra: jaeger
Requires-Dist: opentelemetry-exporter-jaeger>=1.21.0; extra == 'jaeger'
Provides-Extra: pytest
Requires-Dist: pytest-asyncio>=0.21.1; extra == 'pytest'
Requires-Dist: pytest>=7.4.0; extra == 'pytest'
